{"root": {"nodes": [{"inputs": [{"bDirty": true, "name": "input", "dataType": 5, "type": 0, "value": 0, "bLabelHidden": false, "uuid": "c9b8a132-f110-4c79-ab54-1f8fdfb499cf"}], "meta": {"label": "RequestNode"}, "name": "RequestNode", "outputs": [], "y": 4768.0, "x": 5070.0, "computeCode": "def compute(self):\n    # check if any dirty nodes before connected Pin.\n    # randint for example\n    # if so push forward and recompute\n    behind_dirty_ports = [p for p in find_ports_behind(self.input) if p.dirty is True]\n    shouldRecalc = (not len(behind_dirty_ports) == 0)\n    if shouldRecalc:\n        # push from dirty ports\n        # request data\n        for p in behind_dirty_ports:\n            push(p)\n    data = self.input.getData()\n    self.graph().writeToConsole(str(data))\n    print(str(data))\n", "type": "RequestNode", "uuid": "6972e64f-b83e-4513-831d-8290f92adb50"}, {"inputs": [], "meta": {"varuuid": "d35a67e0-4087-4bb3-a3df-50e2cdab7399", "label": "state"}, "name": "state", "outputs": [{"bDirty": true, "name": "val", "dataType": 1, "type": 1, "value": 0, "bLabelHidden": true, "uuid": "26b84dac-2e74-4b66-bf74-953e4832950e"}], "y": 4798.0, "x": 4840.0, "computeCode": "def compute(self):\n    self.out.setData(self.var.value)\n", "type": "GetVarNode", "uuid": "7d37b6dc-7431-4285-a16d-c050ef4527f1"}], "edges": [{"sourceName": "state.val", "sourceUUID": "26b84dac-2e74-4b66-bf74-953e4832950e", "destinationName": "RequestNode.input", "destinationUUID": "c9b8a132-f110-4c79-ab54-1f8fdfb499cf"}], "variables": [{"type": 1, "name": "state", "value": 0, "uuid": "d35a67e0-4087-4bb3-a3df-50e2cdab7399"}]}}